genome_kit/__init__.py
genome_kit/__main__.py
genome_kit/_apply_variants.py
genome_kit/_build_annotations.py
genome_kit/_build_appris.py
genome_kit/_build_mane.py
genome_kit/_cxx.cpython-312-x86_64-linux-gnu.so
genome_kit/_cxx_util.py
genome_kit/_gk_data_config.py
genome_kit/_twobitutils.py
genome_kit/_util.py
genome_kit/data_manager.py
genome_kit/genome.py
genome_kit/genome_annotation.py
genome_kit/genome_dna.py
genome_kit/genome_track.py
genome_kit/gk_data.py
genome_kit/interval.py
genome_kit/jralign.py
genome_kit/jrdist.py
genome_kit/marshal.py
genome_kit/ralign.py
genome_kit/serialize.py
genome_kit/variant.py
genome_kit/variant_genome.py
genome_kit/vcf_table.py
genomekit-7.2.1.dist-info/METADATA
genomekit-7.2.1.dist-info/WHEEL
genomekit-7.2.1.dist-info/top_level.txt
genomekit-7.2.1.dist-info/RECORD
genomekit-7.2.1.dist-info/licenses/COPYRIGHT.txt
genomekit-7.2.1.dist-info/licenses/LICENSE
